rainiee_data/__init__.py
rainiee_data/data_pro.py
rainiee_data/base/__init__.py
rainiee_data/base/client.py
rainiee_data/base/login.py
rainiee_data/base/upass.py
rainiee_data-3.0.2.dist-info/METADATA
rainiee_data-3.0.2.dist-info/WHEEL
rainiee_data-3.0.2.dist-info/top_level.txt
rainiee_data-3.0.2.dist-info/RECORD
