Metadata-Version: 2.1
Name: rainiee-data
Version: 3.0.2
Summary: rainiee basic data api
Home-page: https://github.com/Rainiee-Technology/rainiee_algorithm
Author: rainiee
Author-email: rainiee@163.com
License: MIT
Requires-Python: >=3
